certbot_apache/__init__.py
certbot_apache/py.typed
certbot_apache/_internal/__init__.py
certbot_apache/_internal/apache_util.py
certbot_apache/_internal/apacheparser.py
certbot_apache/_internal/assertions.py
certbot_apache/_internal/augeasparser.py
certbot_apache/_internal/configurator.py
certbot_apache/_internal/constants.py
certbot_apache/_internal/display_ops.py
certbot_apache/_internal/dualparser.py
certbot_apache/_internal/entrypoint.py
certbot_apache/_internal/http_01.py
certbot_apache/_internal/interfaces.py
certbot_apache/_internal/obj.py
certbot_apache/_internal/override_alpine.py
certbot_apache/_internal/override_arch.py
certbot_apache/_internal/override_centos.py
certbot_apache/_internal/override_darwin.py
certbot_apache/_internal/override_debian.py
certbot_apache/_internal/override_fedora.py
certbot_apache/_internal/override_gentoo.py
certbot_apache/_internal/override_suse.py
certbot_apache/_internal/override_void.py
certbot_apache/_internal/parser.py
certbot_apache/_internal/parsernode_util.py
certbot_apache/_internal/augeas_lens/httpd.aug
certbot_apache/_internal/tests/__init__.py
certbot_apache/_internal/tests/augeasnode_test.py
certbot_apache/_internal/tests/autohsts_test.py
certbot_apache/_internal/tests/centos_test.py
certbot_apache/_internal/tests/complex_parsing_test.py
certbot_apache/_internal/tests/configurator_reverter_test.py
certbot_apache/_internal/tests/configurator_test.py
certbot_apache/_internal/tests/conftest.py
certbot_apache/_internal/tests/debian_test.py
certbot_apache/_internal/tests/display_ops_test.py
certbot_apache/_internal/tests/dualnode_test.py
certbot_apache/_internal/tests/entrypoint_test.py
certbot_apache/_internal/tests/fedora_test.py
certbot_apache/_internal/tests/gentoo_test.py
certbot_apache/_internal/tests/http_01_test.py
certbot_apache/_internal/tests/obj_test.py
certbot_apache/_internal/tests/parser_test.py
certbot_apache/_internal/tests/parsernode_configurator_test.py
certbot_apache-5.1.0.dist-info/licenses/LICENSE.txt
certbot_apache-5.1.0.dist-info/METADATA
certbot_apache-5.1.0.dist-info/WHEEL
certbot_apache-5.1.0.dist-info/entry_points.txt
certbot_apache-5.1.0.dist-info/top_level.txt
certbot_apache-5.1.0.dist-info/RECORD
